cerelink-8.0.2.dist-info/WHEEL
cerelink-8.0.2.dist-info/top_level.txt
cerelink-8.0.2.dist-info/METADATA
cerelink-8.0.2.dist-info/RECORD
cerelink/cbsdk_cython.pxd
cerelink/cbpy.pyx
cerelink/cbpy.cpython-311-aarch64-linux-gnu.so
cerelink/cbsdk_helper.cpp
cerelink/__version__.py
cerelink/__init__.py
cerelink/cbsdk_helper.h
