Metadata-Version: 2.4
Name: cerelink
Version: 8.0.2
Author: Ehsan Azar
Author-email: Chadwick Boulay <chadwick.boulay@gmail.com>
Project-URL: homepage, https://github.com/CerebusOSS/CereLink
Requires-Python: >=3.11
Requires-Dist: numpy>=2.0.0
